.gitignore
LICENSE
MANIFEST.in
README.rst
setup.py
docs/Makefile
docs/code.rst
docs/conf.py
docs/index.rst
docs/_build/dummy
docs/_static/dummy
docs/_templates/dummy
m7pub_pylibs/__init__.py
m7pub_pylibs/common.py
m7pub_pylibs.egg-info/PKG-INFO
m7pub_pylibs.egg-info/SOURCES.txt
m7pub_pylibs.egg-info/dependency_links.txt
m7pub_pylibs.egg-info/top_level.txt
m7pub_pylibs/dev/__init__.py
m7pub_pylibs/dev/debug.py
m7pub_pylibs/dev/test/Makefile
m7pub_pylibs/jp/__init__.py
m7pub_pylibs/jp/mobemail.py
m7pub_pylibs/jp/str.py
m7pub_pylibs/jp/test/Makefile
m7pub_pylibs/jp/test/test_str.py
m7pub_pylibs/utils/__init__.py
m7pub_pylibs/utils/data.py
m7pub_pylibs/utils/files.py
m7pub_pylibs/utils/helpers.py
m7pub_pylibs/utils/str.py
m7pub_pylibs/utils/www.py
m7pub_pylibs/utils/test/Makefile