Metadata-Version: 1.0
Name: m7pub-pylibs
Version: 1.1.4
Summary: m7pub_pylibs are libraries used by MARIMORE and are opened sourced
Home-page: UNKNOWN
Author: Iqbal Abdullah
Author-email: iqbal@marimore.co.jp
License: LICENSE.txt
Platform: UNKNOWN
